{
  "author": {
    "email": "brunosmmm@gmail.com",
    "name": "Bruno Morais"
  },
  "data": {
    "annotation_id": "ann_030332_fc7bec",
    "complexity_delta": -0.24,
    "git_branch": "main",
    "resolution_approach": "code",
    "resolution_outcome": "success",
    "resolution_summary": "Added 30-second turn timer: backend tracks turn_started_at, background task checks timeouts and auto-plays random valid move or passes. Frontend shows circular timer in mobile header and progress bar in desktop sidebar.",
    "retrospective_complexity": 0.41,
    "session_id": "20260127_175528_81e5"
  },
  "entity_id": "task_185355_b31c32",
  "lamport_clock": 92,
  "operation_id": "op_20260131_010447_b7c9c09a",
  "operation_type": "task_complete",
  "parent_operation": null,
  "timestamp": "2026-01-27T18:58:08.802674+00:00"
}